nelux/batch.py
nelux/py.typed
nelux/_nelux.pyd
nelux/_nelux.pyi
nelux/__init__.py
nelux-0.8.7.dist-info/DELVEWHEEL
nelux-0.8.7.dist-info/METADATA
nelux-0.8.7.dist-info/RECORD
nelux-0.8.7.dist-info/WHEEL
nelux-0.8.7.dist-info/licenses/LICENSE
nelux.libs/jpeg62-480568147b9b02496770d2b714077e58.dll
nelux.libs/libyuv-570d037feb9ca87a402f4e89aad43ed2.dll
nelux.libs/msvcp140-2a7008da6f9aae43c7a434835dcaf31e.dll
