Metadata-Version: 2.2
Name: nelux
Version: 0.8.7
Summary: Lightspeed video decoding directly into tensors!
Keywords: ffmpeg,video,ml,pytorch,decode,tensors,inference
Author-Email: Nilas Tiago <nilascontact@gmail.com>
License: AGPL-3.0
Classifier: Programming Language :: Python :: 3
Classifier: License :: OSI Approved :: GNU Affero General Public License v3
Classifier: Operating System :: Microsoft :: Windows
Classifier: Operating System :: POSIX :: Linux
Project-URL: Homepage, https://github.com/NevermindNilas/Nelux
Project-URL: Repository, https://github.com/NevermindNilas/Nelux
Project-URL: Documentation, https://github.com/NevermindNilas/Nelux/blob/master/README.md
Project-URL: Changelog, https://github.com/NevermindNilas/Nelux/blob/master/docs/CHANGELOG.md
Project-URL: Issues, https://github.com/NevermindNilas/Nelux/issues
Requires-Python: >=3.13
